ezreader/__init__.py
ezreader/simulation.py
ezreader/utilities.py
ezreader-0.1.dist-info/METADATA
ezreader-0.1.dist-info/WHEEL
ezreader-0.1.dist-info/top_level.txt
ezreader-0.1.dist-info/RECORD
